curator/__init__.py
curator/_version.py
curator/classdef.py
curator/cli.py
curator/exceptions.py
curator/indexlist.py
curator/repomgrcli.py
curator/singletons.py
curator/snapshotlist.py
curator/actions/__init__.py
curator/actions/alias.py
curator/actions/allocation.py
curator/actions/close.py
curator/actions/cluster_routing.py
curator/actions/cold2frozen.py
curator/actions/create_index.py
curator/actions/delete_indices.py
curator/actions/forcemerge.py
curator/actions/index_settings.py
curator/actions/open.py
curator/actions/reindex.py
curator/actions/replicas.py
curator/actions/rollover.py
curator/actions/shrink.py
curator/actions/snapshot.py
curator/cli_singletons/__init__.py
curator/cli_singletons/alias.py
curator/cli_singletons/allocation.py
curator/cli_singletons/close.py
curator/cli_singletons/delete.py
curator/cli_singletons/forcemerge.py
curator/cli_singletons/object_class.py
curator/cli_singletons/open_indices.py
curator/cli_singletons/replicas.py
curator/cli_singletons/restore.py
curator/cli_singletons/rollover.py
curator/cli_singletons/show.py
curator/cli_singletons/shrink.py
curator/cli_singletons/snapshot.py
curator/cli_singletons/utils.py
curator/defaults/__init__.py
curator/defaults/filter_elements.py
curator/defaults/filtertypes.py
curator/defaults/option_defaults.py
curator/defaults/settings.py
curator/helpers/__init__.py
curator/helpers/date_ops.py
curator/helpers/getters.py
curator/helpers/testers.py
curator/helpers/utils.py
curator/helpers/waiters.py
curator/validators/__init__.py
curator/validators/actions.py
curator/validators/filter_functions.py
curator/validators/options.py
elasticsearch_curator-9.0.0.dist-info/METADATA
elasticsearch_curator-9.0.0.dist-info/WHEEL
elasticsearch_curator-9.0.0.dist-info/entry_points.txt
elasticsearch_curator-9.0.0.dist-info/licenses/LICENSE
elasticsearch_curator-9.0.0.dist-info/licenses/NOTICE
elasticsearch_curator-9.0.0.dist-info/RECORD
