Metadata-Version: 2.3
Name: elasticsearch-curator
Version: 9.0.0
Summary: Tending your Elasticsearch indices and snapshots
Project-URL: Homepage, https://github.com/elastic/curator
Project-URL: Bug Tracker, https://github.com/elastic/curator/issues
Author-email: Elastic <info@elastic.co>
License: Copyright 2011–2024 Elasticsearch <http://elastic.co> and contributors.
License-File: LICENSE
License-File: NOTICE
Keywords: elasticsearch,index-expiry,indexed,time-series
Classifier: Intended Audience :: Developers
Classifier: Intended Audience :: System Administrators
Classifier: License :: OSI Approved :: Apache Software License
Classifier: Operating System :: OS Independent
Classifier: Programming Language :: Python
Classifier: Programming Language :: Python :: 3.10
Classifier: Programming Language :: Python :: 3.11
Classifier: Programming Language :: Python :: 3.12
Classifier: Programming Language :: Python :: 3.13
Requires-Python: >=3.10
Requires-Dist: es-client==9.0.1
Provides-Extra: doc
Requires-Dist: sphinx; extra == 'doc'
Requires-Dist: sphinx-rtd-theme; extra == 'doc'
Provides-Extra: test
Requires-Dist: pytest-cov; extra == 'test'
Requires-Dist: pytest>=7.2.1; extra == 'test'
Requires-Dist: requests; extra == 'test'
